MANIFEST.in
README.md
README.rst
setup.cfg
setup.py
jccli/__init__.py
jccli/config.py
jccli/errors.py
jccli/helpers.py
jccli/jc_api_v1.py
jccli/jc_api_v2.py
jccli/version.py
jccli.egg-info/PKG-INFO
jccli.egg-info/SOURCES.txt
jccli.egg-info/dependency_links.txt
jccli.egg-info/entry_points.txt
jccli.egg-info/requires.txt
jccli.egg-info/top_level.txt
jccli/cli/__init__.py
jccli/cli/group.py
jccli/cli/sync.py
jccli/cli/system.py
jccli/cli/user.py