Metadata-Version: 2.1
Name: jccli
Version: 0.0.18
Summary: A Jumpcloud command line client
Home-page: https://github.com/Sage-Bionetworks/jccli
Author: sageit
Author-email: it@sagebase.org
License: Apache Software License
Download-URL: https://github.com/Sage-Bionetworks/jccli/archive/0.0.18.tar.gz
Keywords: jccli,jumpcloud,cli,idp
Platform: UNKNOWN
Classifier: Development Status :: 4 - Beta
Classifier: Intended Audience :: Developers
Classifier: Natural Language :: English
Classifier: Environment :: Console
Classifier: License :: OSI Approved :: Apache Software License
Classifier: Programming Language :: Python :: 3.6
Requires-Python: >=3
